Metadata-Version: 2.1
Name: libra-core-base
Version: 0.0.27
Summary: Basic components for libra or others
Home-page: UNKNOWN
Author: apus
License: BSD License
Platform: UNKNOWN
Classifier: Intended Audience :: Developers
Classifier: License :: OSI Approved :: BSD License
Classifier: Operating System :: OS Independent
Classifier: Programming Language :: Python
Classifier: Programming Language :: Python :: 3.8
Classifier: Topic :: Internet :: WWW/HTTP
Classifier: Topic :: Internet :: WWW/HTTP :: Dynamic Content
Requires-Dist: pika (==1.1.0)
Requires-Dist: influxdb (==5.3.1)
